aldryn_search/__init__.py
aldryn_search/apps.py
aldryn_search/base.py
aldryn_search/cms_apps.py
aldryn_search/compat.py
aldryn_search/conf.py
aldryn_search/helpers.py
aldryn_search/models.py
aldryn_search/receivers.py
aldryn_search/router.py
aldryn_search/search_indexes.py
aldryn_search/signal_processor.py
aldryn_search/signals.py
aldryn_search/urls.py
aldryn_search/utils.py
aldryn_search/views.py
aldryn_search/locale/en/LC_MESSAGES/django.mo
aldryn_search/locale/en/LC_MESSAGES/django.po
aldryn_search/templates/aldryn_search/base.html
aldryn_search/templates/aldryn_search/search_results.html
aldryn_search/templates/aldryn_search/includes/pagination.html
aldryn_search/templates/aldryn_search/includes/search_items.html
djangocms_aldryn_search-3.1.0.dist-info/licenses/LICENSE
djangocms_aldryn_search-3.1.0.dist-info/METADATA
djangocms_aldryn_search-3.1.0.dist-info/WHEEL
djangocms_aldryn_search-3.1.0.dist-info/top_level.txt
djangocms_aldryn_search-3.1.0.dist-info/RECORD
