Metadata-Version: 2.4
Name: djangocms-aldryn-search
Version: 3.1.0
Summary: An extension to django CMS to provide multilingual Haystack indexes.
Home-page: https://github.com/CZ-NIC/djangocms-aldryn-search
Author: Benjamin Wohlwend
Author-email: piquadrat@gmail.com
License: BSD License
Classifier: Development Status :: 5 - Production/Stable
Classifier: Environment :: Web Environment
Classifier: Intended Audience :: Developers
Classifier: Operating System :: OS Independent
Classifier: Framework :: Django
Classifier: Framework :: Django :: 4.0
Classifier: Framework :: Django :: 5.0
Classifier: Programming Language :: Python :: 3
Classifier: Programming Language :: Python :: 3.10
Classifier: Programming Language :: Python :: 3.11
Classifier: Programming Language :: Python :: 3.12
Classifier: Topic :: Internet :: WWW/HTTP
Classifier: Topic :: Internet :: WWW/HTTP :: Dynamic Content
Classifier: Topic :: Software Development
Classifier: Topic :: Software Development :: Libraries
Requires-Python: >=3.10
License-File: LICENSE
Requires-Dist: lxml~=6.0
Requires-Dist: lxml-html-clean~=0.4
Requires-Dist: django-appconf~=1.1
Requires-Dist: django-cms<6,>=4.1
Requires-Dist: djangocms-versioning~=2.4
Requires-Dist: django-haystack~=3.3
Requires-Dist: django-spurl~=0.6
Requires-Dist: django-standard-form~=1.1
Requires-Dist: djangocms-aldryn-common~=2.0
Requires-Dist: looseversion~=1.3
Dynamic: author
Dynamic: author-email
Dynamic: classifier
Dynamic: description
Dynamic: description-content-type
Dynamic: home-page
Dynamic: license
Dynamic: license-file
Dynamic: requires-dist
Dynamic: requires-python
Dynamic: summary
